LICENSE
data_grid_surface/__init__.py
data_grid_surface/config/__init__.py
data_grid_surface/config/config.py
data_grid_surface/data_grid.py
data_grid_surface/services/hash.py
data_grid_surface-1.2.0.dist-info/LICENSE
data_grid_surface-1.2.0.dist-info/WHEEL
data_grid_surface-1.2.0.dist-info/METADATA
data_grid_surface-1.2.0.dist-info/RECORD
