Metadata-Version: 2.1
Name: data-grid-surface
Version: 1.2.0
Summary: SDK to communicate with data-grid API
License: MIT
Keywords: data,grid,surface,breach
Author: DataGrid Dev Team
Author-email: dev@datagridsurface.com
Requires-Python: >=3.8,<4.0
Classifier: License :: OSI Approved :: MIT License
Classifier: Operating System :: OS Independent
Classifier: Programming Language :: Python :: 3
Classifier: Programming Language :: Python :: 3.8
Classifier: Programming Language :: Python :: 3.9
Classifier: Topic :: Software Development :: Libraries :: Python Modules
Requires-Dist: python-dotenv (>=0.17.0,<0.18.0)
Requires-Dist: requests (>=2.25.1,<3.0.0)
